[
    {
      "username": "admin",
      "password": "badgerscan#",
      "type": "admin"
    },
    {
      "username": "lclark@badgerinventory.com",
      "password": "3684",
      "type": "user",
      "displayName": "lashaun"
    },
    {
      "username": "kimtest",
      "password": "1234",
      "type": "user",
      "displayName": "kim"
    },
    {
        "username": "djtest",
        "password": "1234",
        "type": "user",
        "displayName": "dj"
      },
      {
        "username": "iantest",
        "password": "1234",
        "type": "user",
        "displayName": "ian"
      },
      {
        "username": "maitest",
        "password": "1234",
        "type": "user",
        "displayName": "mai"
      },
      {
        "username": "mom",
        "password": "mom",
        "type": "user",
        "displayName": "lashaun"
      },
      {
        "username": "aivy",
        "password": "aivy",
        "type": "user",
        "displayName": "lashaun"
      }
  ]
  